<?xml version="1.0" encoding="UTF-8"?>
<!DOCTYPE suite SYSTEM "http://testng.org/testng-1.0.dtd"><suite name="All Test Suite"><test verbose="2" preserve-order="true" name="/home/user01/IdeaProjects/Demo/src/test/java/TestSuite/TestSuite_LoginPage.java"><classes><class name="TestSuite.TestSuite_LoginPage"><methods><include name="TC_001_ValidateSucessFullLogin"/></methods></class></classes></test><test verbose="2" preserve-order="true" name="/home/user01/IdeaProjects/Demo/testng.xml"><classes/></test><test verbose="2" preserve-order="true" name="/home/user01/IdeaProjects/Demo/src/test/java/TestSuite/TestSuite_TopCategoryHp.java"><classes><class name="TestSuite.TestSuite_TopCategoryHp"><methods><include name="verify_TopCategory"/></methods></class></classes></test><test verbose="2" preserve-order="true" name="/home/user01/IdeaProjects/Demo/src/test/java/TestSuite/TestSuite_userTracking.java"><classes><class name="TestSuite.TestSuite_userTracking"><methods><include name="TC_001LoggedInManufacturesPage"/><include name="TC_002LoggedInCityPage"/><include name="TC_003LoggedInSerchPage"/><include name="TC_004LoggedInSellerListing"/><include name="TC_005CityPage"/><include name="TC_006NotLoggedSearchPage"/><include name="TC_007NotLoggedSellerListingPage"/><include name="TC_008NotLoggedCityPage"/></methods></class></classes></test></suite>